CHANGES.rst
CONTRIBUTING.rst
DEVEL.rst
MANIFEST.in
README.rst
setup.cfg
setup.py
Products/__init__.py
Products.LinguaPlone.egg-info/PKG-INFO
Products.LinguaPlone.egg-info/SOURCES.txt
Products.LinguaPlone.egg-info/dependency_links.txt
Products.LinguaPlone.egg-info/namespace_packages.txt
Products.LinguaPlone.egg-info/not-zip-safe
Products.LinguaPlone.egg-info/requires.txt
Products.LinguaPlone.egg-info/top_level.txt
Products/LinguaPlone/I18NBaseBTreeFolder.py
Products/LinguaPlone/I18NBaseContent.py
Products/LinguaPlone/I18NBaseFolder.py
Products/LinguaPlone/I18NBaseObject.py
Products/LinguaPlone/I18NOrderedBaseFolder.py
Products/LinguaPlone/LanguageIndex.py
Products/LinguaPlone/README.txt
Products/LinguaPlone/__init__.py
Products/LinguaPlone/caching.py
Products/LinguaPlone/catalog.py
Products/LinguaPlone/config.py
Products/LinguaPlone/configure.zcml
Products/LinguaPlone/events.py
Products/LinguaPlone/interfaces.py
Products/LinguaPlone/patches.py
Products/LinguaPlone/permissions.py
Products/LinguaPlone/public.py
Products/LinguaPlone/setuphandlers.py
Products/LinguaPlone/upgrades.py
Products/LinguaPlone/upgrades.zcml
Products/LinguaPlone/utils.py
Products/LinguaPlone/vocabulary.py
Products/LinguaPlone/browser/__init__.py
Products/LinguaPlone/browser/configure.zcml
Products/LinguaPlone/browser/contentlinkviewlet.pt
Products/LinguaPlone/browser/contentlinkviewlet.py
Products/LinguaPlone/browser/controlpanel.py
Products/LinguaPlone/browser/defaultpage.py
Products/LinguaPlone/browser/interfaces.py
Products/LinguaPlone/browser/language.pt
Products/LinguaPlone/browser/language.py
Products/LinguaPlone/browser/menu.py
Products/LinguaPlone/browser/selector.pt
Products/LinguaPlone/browser/selector.py
Products/LinguaPlone/browser/setup.py
Products/LinguaPlone/browser/switcher.py
Products/LinguaPlone/browser/translate.py
Products/LinguaPlone/browser/vocabularies.py
Products/LinguaPlone/criteria/README.txt
Products/LinguaPlone/criteria/__init__.py
Products/LinguaPlone/criteria/configure.zcml
Products/LinguaPlone/criteria/interfaces.py
Products/LinguaPlone/criteria/syncer.py
Products/LinguaPlone/criteria/tests.py
Products/LinguaPlone/exportimport/LanguageIndex.py
Products/LinguaPlone/exportimport/__init__.py
Products/LinguaPlone/exportimport/configure.zcml
