Metadata-Version: 1.1
Name: Products.LinguaPlone
Version: 4.3.0
Summary: Manage and maintain multilingual content that integrates seamlessly with Plone.
Home-page: https://pypi.python.org/pypi/Products.LinguaPlone
Author: Plone Foundation
Author-email: plone-developers@lists.sourceforge.net
License: GPL version 2
Keywords: Zope Plone multilingual translation
Platform: UNKNOWN
Classifier: Environment :: Web Environment
Classifier: Framework :: Plone
Classifier: Framework :: Plone :: 4.3
Classifier: Framework :: Zope2
Classifier: License :: OSI Approved :: GNU General Public License (GPL)
Classifier: Operating System :: OS Independent
Classifier: Programming Language :: Python
Classifier: Programming Language :: Python :: 2.6
Classifier: Programming Language :: Python :: 2.7
